wbcommission/__init__.py
wbcommission/apps.py
wbcommission/dynamic_preferences_registry.py
wbcommission/permissions.py
wbcommission/urls.py
wbcommission/admin/__init__.py
wbcommission/admin/accounts.py
wbcommission/admin/commission.py
wbcommission/admin/rebate.py
wbcommission/analytics/__init__.py
wbcommission/analytics/marginality.py
wbcommission/factories/__init__.py
wbcommission/factories/commission.py
wbcommission/factories/rebate.py
wbcommission/filters/__init__.py
wbcommission/filters/rebate.py
wbcommission/filters/signals.py
wbcommission/generators/__init__.py
wbcommission/generators/rebate_generator.py
wbcommission/migrations/0001_initial.py
wbcommission/migrations/0002_commissionrule_remove_accountcustomer_account_and_more.py
wbcommission/migrations/0003_alter_commission_account.py
wbcommission/migrations/0004_rebate_audit_log.py
wbcommission/migrations/0005_alter_rebate_audit_log.py
wbcommission/migrations/0006_commissionrule_consider_zero_percent_for_exclusion.py
wbcommission/migrations/0007_remove_commission_unique_crm_recipient_account_and_more.py
wbcommission/migrations/0008_alter_commission_options_alter_commission_order.py
wbcommission/migrations/__init__.py
wbcommission/models/__init__.py
wbcommission/models/account_service.py
wbcommission/models/commission.py
wbcommission/models/rebate.py
wbcommission/models/signals.py
wbcommission/reports/__init__.py
wbcommission/reports/audit_report.py
wbcommission/reports/customer_report.py
wbcommission/reports/utils.py
wbcommission/serializers/__init__.py
wbcommission/serializers/commissions.py
wbcommission/serializers/rebate.py
wbcommission/serializers/signals.py
wbcommission/tests/__init__.py
wbcommission/tests/conftest.py
wbcommission/tests/signals.py
wbcommission/tests/test_permissions.py
wbcommission/tests/analytics/__init__.py
wbcommission/tests/analytics/test_marginality.py
wbcommission/tests/models/__init__.py
wbcommission/tests/models/mixins.py
wbcommission/tests/models/test_account_service.py
wbcommission-2.2.6.dist-info/METADATA
wbcommission-2.2.6.dist-info/WHEEL
wbcommission-2.2.6.dist-info/RECORD
