Metadata-Version: 2.4
Name: wbcommission
Version: 2.2.6
Summary: A workbench module for managing human resources.
Author-email: Christopher Wittlinger <c.wittlinger@stainly.com>
Requires-Dist: reportlab==3.*
Requires-Dist: wbcompliance
Requires-Dist: wbcore
Requires-Dist: wbcrm
Requires-Dist: wbfdm
Requires-Dist: wbnews
